gitql/__init__.py
gitql/ast.py
gitql/errors.py
gitql/gitql.py
gitql/lexer.py
gitql/main.py
gitql/parser.py
gitql/semantical.py
gitql/token.py
gitql/visitor.py
gitql-1.0.5.dist-info/DESCRIPTION.rst
gitql-1.0.5.dist-info/METADATA
gitql-1.0.5.dist-info/RECORD
gitql-1.0.5.dist-info/WHEEL
gitql-1.0.5.dist-info/entry_points.txt
gitql-1.0.5.dist-info/metadata.json
gitql-1.0.5.dist-info/top_level.txt
prettytable/__init__.py
prettytable/prettytable.py
