Metadata-Version: 2.0
Name: gitql
Version: 1.0.5
Summary: A git query language
Home-page: https://github.com/mackong/gitql
Author: MacKong
Author-email: mackonghp@gmail.com
License: MIT
Download-URL: https://github.com/mackong/gitql/tarball/1.0.5
Keywords: git gitql
Platform: UNKNOWN
Classifier: Development Status :: 4 - Beta
Classifier: Environment :: Console
Classifier: Intended Audience :: Developers
Classifier: Programming Language :: Python :: 2
Classifier: Programming Language :: Python :: 2.7
Classifier: Programming Language :: Python :: 3
Classifier: Programming Language :: Python :: 3.3
Classifier: Programming Language :: Python :: 3.4
Classifier: Programming Language :: Python :: 3.5
Classifier: Programming Language :: Python :: 3.6
Classifier: Topic :: Documentation
Requires-Dist: GitPython
Requires-Dist: termcolor
Requires-Dist: enum34
